dj_maker/__init__.py
dj_maker/main.py
dj_maker/generators/__init__.py
dj_maker/generators/models.py
dj_maker/generators/templates.py
dj_maker/generators/urls.py
dj_maker/generators/views.py
dj_maker/templates/html/base.html.j2
dj_maker/templates/html/confirm_delete.html.j2
dj_maker/templates/html/detail.html.j2
dj_maker/templates/html/form.html.j2
dj_maker/templates/html/list.html.j2
dj_maker/templates/serializers/model_serializer.py.j2
dj_maker/templates/urls/api.py.j2
dj_maker/templates/urls/standard.py.j2
dj_maker/templates/views/api_views.py.j2
dj_maker/templates/views/class_based.py.j2
dj_maker/templates/views/function_based.py.j2
dj_maker-0.2.0.dist-info/METADATA
dj_maker-0.2.0.dist-info/WHEEL
dj_maker-0.2.0.dist-info/entry_points.txt
dj_maker-0.2.0.dist-info/licenses/LICENSE
dj_maker-0.2.0.dist-info/RECORD
