Metadata-Version: 2.4
Name: dj-maker
Version: 0.2.0
Summary: A lightweight Django project generator for rapid scaffolding of apps, models, and templates. Ideal for developers seeking to streamline Django setup and code generation.
Author-email: Giacomo Barbalinardo <info@ready24it.eu>
License-File: LICENSE
Classifier: Development Status :: 4 - Beta
Classifier: Environment :: Web Environment
Classifier: Framework :: Django
Classifier: Framework :: Django :: 4.2
Classifier: Framework :: Django :: 5.1
Classifier: Framework :: Django :: 5.2
Classifier: Intended Audience :: Developers
Classifier: License :: OSI Approved :: MIT License
Classifier: Operating System :: OS Independent
Classifier: Programming Language :: Python
Classifier: Programming Language :: Python :: 3
Classifier: Programming Language :: Python :: 3.10
Classifier: Programming Language :: Python :: 3.11
Classifier: Programming Language :: Python :: 3.12
Classifier: Programming Language :: Python :: 3.13
Classifier: Topic :: Internet :: WWW/HTTP
Classifier: Topic :: Internet :: WWW/HTTP :: Dynamic Content
Classifier: Topic :: Software Development :: Code Generators
Classifier: Topic :: Software Development :: Libraries :: Python Modules
Requires-Python: >=3.13
Requires-Dist: django<6.0,>=4.2
Requires-Dist: jinja2>=3.1.6
Requires-Dist: rich>=14.1.0
Requires-Dist: typer>=0.16.0
